LICENSE
MANIFEST.in
README.md
pyproject.toml
setup.py
ci/310-conda.yaml
ci/311-conda.yaml
ci/312-conda.yaml
ci/39-conda.yaml
proto/fileformat.proto
proto/osmformat.proto
pyrobuf/_proto/pyrosm_proto.c
pyrobuf/_proto/pyrosm_proto.pxd
pyrobuf/_proto/pyrosm_proto.pyx
pyrosm/__init__.py
pyrosm/_arrays.c
pyrosm/_arrays.pxd
pyrosm/_arrays.pyx
pyrosm/boundary.py
pyrosm/buildings.py
pyrosm/data_filter.c
pyrosm/data_filter.pxd
pyrosm/data_filter.pyx
pyrosm/data_manager.c
pyrosm/data_manager.pxd
pyrosm/data_manager.pyx
pyrosm/delta_compression.c
pyrosm/delta_compression.pxd
pyrosm/delta_compression.pyx
pyrosm/distance.py
pyrosm/frames.c
pyrosm/frames.pxd
pyrosm/frames.pyx
pyrosm/geometry.c
pyrosm/geometry.pxd
pyrosm/geometry.pyx
pyrosm/graph_connectivity.py
pyrosm/graph_export.c
pyrosm/graph_export.pxd
pyrosm/graph_export.pyx
pyrosm/graphs.py
pyrosm/landuse.py
pyrosm/natural.py
pyrosm/networks.py
pyrosm/pbfreader.c
pyrosm/pbfreader.pxd
pyrosm/pbfreader.pyx
pyrosm/pois.py
pyrosm/pyrosm.py
pyrosm/relations.c
pyrosm/relations.pxd
pyrosm/relations.pyx
pyrosm/tagparser.c
pyrosm/tagparser.pxd
pyrosm/tagparser.pyx
pyrosm/user_defined.py
pyrosm.egg-info/PKG-INFO
pyrosm.egg-info/SOURCES.txt
pyrosm.egg-info/dependency_links.txt
pyrosm.egg-info/not-zip-safe
pyrosm.egg-info/requires.txt
pyrosm.egg-info/top_level.txt
pyrosm/config/__init__.py
pyrosm/config/default_tags.py
pyrosm/config/osm_filters.py
pyrosm/data/Helsinki.osm.pbf
pyrosm/data/__init__.py
pyrosm/data/bbbike.py
pyrosm/data/geofabrik.py
pyrosm/data/test.osm.pbf
pyrosm/exceptions/__init__.py
pyrosm/utils/__init__.py
pyrosm/utils/_compat.py
pyrosm/utils/download.py
tests/test_a_poi.py
tests/test_boundary_parsing.py
tests/test_building_parsing.py
tests/test_custom_filter.py
tests/test_data.py
tests/test_distance_calculation.py
tests/test_filters.py
tests/test_graph_exports.py
tests/test_landuse_parsing.py
tests/test_main.py
tests/test_natural_parsing.py
tests/test_network_parsing.py
tests/test_pbf_parsing.py
tests/test_utils.py