Metadata-Version: 2.1
Name: pyrosm
Version: 0.6.2
Summary: A Python tool to parse OSM data from Protobuf format into GeoDataFrame.
Home-page: https://pyrosm.readthedocs.io/
Author: Henrikki Tenkanen
Author-email: henrikki.tenkanen@aalto.fi
License: MIT
Project-URL: Documentation, https://pyrosm.github.io/
Project-URL: Issue Tracker, https://github.com/htenkanen/pyrosm/issues
Keywords: OpenStreetMap,Geopandas,GeoDataFrame,parser,protobuf,PBF
Classifier: Development Status :: 3 - Alpha
Classifier: Intended Audience :: Developers
Classifier: License :: OSI Approved :: MIT License
Classifier: Operating System :: Unix
Classifier: Operating System :: POSIX
Classifier: Operating System :: Microsoft :: Windows
Classifier: Programming Language :: Python
Classifier: Programming Language :: Python :: 3
Classifier: Programming Language :: Python :: 3.9
Classifier: Programming Language :: Python :: 3.10
Classifier: Programming Language :: Python :: 3.11
Classifier: Programming Language :: Python :: 3.12
Classifier: Topic :: Utilities
Requires-Python: >=3.9
License-File: LICENSE
Requires-Dist: python-rapidjson
Requires-Dist: setuptools>=18.0
Requires-Dist: geopandas>=0.12.0
Requires-Dist: shapely>=2.0.1
Requires-Dist: cykhash
Requires-Dist: pyrobuf
